<?xml version="1.0" encoding="utf-16"?>
<TimeLine xmlns:xsd="http://www.w3.org/2001/XMLSchema" xmlns:xsi="http://www.w3.org/2001/XMLSchema-instance">
  <Time>0.9</Time>
  <Points>
    <TimePoint>
      <GUID>89148e43-c2b2-4ef6-a711-2e576a556d52</GUID>
      <Time>0.007352941</Time>
    </TimePoint>
    <TimePoint>
      <GUID>46c8b533-7d3e-44b8-9ee2-b51288868c76</GUID>
      <Time>0.8271208</Time>
    </TimePoint>
    <TimePoint>
      <GUID>0289beab-73e1-4982-8864-76de8f73d750</GUID>
      <Time>0.784318745</Time>
    </TimePoint>
    <TimePoint>
      <GUID>61805086-ce18-41a7-b44a-ac5428a0484d</GUID>
      <Time>0.7785347</Time>
    </TimePoint>
  </Points>
  <Layouts>
    <LayoutBase xsi:type="MotionLayout">
      <GUID>89148e43-c2b2-4ef6-a711-2e576a556d52</GUID>
      <motionName>jump</motionName>
      <targetType>Releaser</targetType>
    </LayoutBase>
    <LayoutBase xsi:type="DamageLayout">
      <GUID>46c8b533-7d3e-44b8-9ee2-b51288868c76</GUID>
      <target>Releaser</target>
      <RangeType>
        <damageType>Rangle</damageType>
        <fiterType>EmenyTeam</fiterType>
        <radius>2.8</radius>
        <angle>360</angle>
        <offsetAngle>0</offsetAngle>
        <offsetPosition>
          <x>0</x>
          <y>0</y>
          <z>0</z>
        </offsetPosition>
      </RangeType>
      <effectType>EffectGroup</effectType>
      <effectKey>001</effectKey>
    </LayoutBase>
    <LayoutBase xsi:type="ParticleLayout">
      <GUID>0289beab-73e1-4982-8864-76de8f73d750</GUID>
      <path>Effects/Pillar Blast/LightningPillarBlast.prefab</path>
      <fromTarget>Releaser</fromTarget>
      <toTarget>Releaser</toTarget>
      <fromBoneName>Bottom</fromBoneName>
      <toBoneName>Body</toBoneName>
      <Bind>false</Bind>
      <destoryType>Time</destoryType>
      <destoryTime>2</destoryTime>
      <offet>
        <x>0</x>
        <y>0</y>
        <z>0</z>
      </offet>
      <rotation>
        <x>0</x>
        <y>0</y>
        <z>0</z>
      </rotation>
      <localsize>1</localsize>
    </LayoutBase>
    <LayoutBase xsi:type="PlaySoundLayout">
      <GUID>61805086-ce18-41a7-b44a-ac5428a0484d</GUID>
      <resourcesPath>Sound/MagicSounds/General Spell/Cast 01.wav</resourcesPath>
      <target>Releaser</target>
      <fromBone>Bottom</fromBone>
      <value>1</value>
    </LayoutBase>
  </Layouts>
</TimeLine>